Devil/DevilTop.py
Devil/__init__.py
Devil/arDev.py
Nasr-19.0.6.dist-info/METADATA
Nasr-19.0.6.dist-info/WHEEL
Nasr-19.0.6.dist-info/top_level.txt
Nasr-19.0.6.dist-info/RECORD
